{"type": "block", "layer": 0, "block": 10, "features": [{"geom": {"pts": [[18.236482201625993, -13.637748910555956, 10.269748377040003]], "r": 0.21969301510154957}, "mtl": 0, "prop": ["9494", "NULL", "Pseudotsuga", "menziesii", "20100316", "NULL", "NULL", "NULL", "NULL", "NULL", "NULL", "NULL", "NULL", "NULL", "NULL"]}, {"geom": {"pts": [[17.657261567250426, -13.815400005814787, 10.250996732093343]], "r": 0.21969301510154957}, "mtl": 0, "prop": ["9492", "NULL", "Pseudotsuga", "menziesii", "20100316", "NULL", "NULL", "NULL", "NULL", "NULL", "NULL", "NULL", "NULL", "NULL", "NULL"]}, {"geom": {"pts": [[17.156786232679178, -14.33729540938267, 10.149178861797942]], "r": 0.21969301510154957}, "mtl": 0, "prop": ["9486", "NULL", "Pseudotsuga", "menziesii", "20100316", "NULL", "NULL", "NULL", "NULL", "NULL", "NULL", "NULL", "NULL", "NULL", "NULL"]}, {"geom": {"pts": [[16.104236997313304, -14.639102350411555, 10.128462798716983]], "r": 0.21969301510154957}, "mtl": 0, "prop": ["9478", "NULL", "Pseudotsuga", "menziesii", "20100316", "NULL", "NULL", "NULL", "NULL", "NULL", "NULL", "NULL", "NULL", "NULL", "NULL"]}, {"geom": {"pts": [[16.364910082928276, -14.794718236176692, 10.09264149994804]], "r": 0.21969301510154957}, "mtl": 0, "prop": ["9477", "NULL", "Pseudotsuga", "menziesii", "20100316", "NULL", "NULL", "NULL", "NULL", "NULL", "NULL", "NULL", "NULL", "NULL", "NULL"]}, {"geom": {"pts": [[15.965691258911964, -14.772463333631888, 10.1034726176817]], "r": 0.21969301510154957}, "mtl": 0, "prop": ["9474", "NULL", "Pseudotsuga", "menziesii", "20100316", "NULL", "NULL", "NULL", "NULL", "NULL", "NULL", "NULL", "NULL", "NULL", "NULL"]}, {"geom": {"pts": [[15.787915671066555, -14.710246271732649, 10.119696666598902]], "r": 0.21969301510154957}, "mtl": 0, "prop": ["9473", "NULL", "Pseudotsuga", "menziesii", "20100316", "NULL", "NULL", "NULL", "NULL", "NULL", "NULL", "NULL", "NULL", "NULL", "NULL"]}, {"geom": {"pts": [[13.304461889842223, -3.8417838293806894, 10.648710112241798]], "r": 0.21969301510154957}, "mtl": 0, "prop": ["8643", "NULL", "Thuja", "plicata", "20100316", "NULL", "NULL", "NULL", "NULL", "NULL", "NULL", "NULL", "NULL", "NULL", "NULL"]}, {"geom": {"pts": [[13.322593886629107, -3.6307613652095587, 10.615623410901279]], "r": 0.21969301510154957}, "mtl": 0, "prop": ["8646", "NULL", "Acer", "macrophyllum", "20100316", "NULL", "NULL", "NULL", "NULL", "NULL", "NULL", "NULL", "NULL", "NULL", "NULL"]}, {"geom": {"pts": [[13.308211317205243, -3.4896818339392732, 10.595200669640713]], "r": 0.21969301510154957}, "mtl": 0, "prop": ["8647", "NULL", "Acer", "macrophyllum", "20100316", "NULL", "NULL", "NULL", "NULL", "NULL", "NULL", "NULL", "NULL", "NULL", "NULL"]}, {"geom": {"pts": [[13.382496848672144, -3.4323419569426608, 10.582288643106939]], "r": 0.21969301510154957}, "mtl": 0, "prop": ["8648", "NULL", "Thuja", "plicata", "20100316", "NULL", "NULL", "NULL", "NULL", "NULL", "NULL", "NULL", "NULL", "NULL", "NULL"]}, {"geom": {"pts": [[13.51903605763206, -3.6217026898615523, 10.601413225796673]], "r": 0.21969301510154957}, "mtl": 0, "prop": ["8650", "NULL", "Thuja", "plicata", "20100316", "NULL", "NULL", "NULL", "NULL", "NULL", "NULL", "NULL", "NULL", "NULL", "NULL"]}, {"geom": {"pts": [[13.678247585659387, -3.396297656317703, 10.55672690355306]], "r": 0.21969301510154957}, "mtl": 0, "prop": ["8651", "NULL", "Thuja", "plicata", "20100316", "NULL", "NULL", "NULL", "NULL", "NULL", "NULL", "NULL", "NULL", "NULL", "NULL"]}, {"geom": {"pts": [[13.800902196083165, -3.4618174365260757, 10.557092298735036]], "r": 0.21969301510154957}, "mtl": 0, "prop": ["8652", "NULL", "Thuja", "plicata", "20100316", "NULL", "NULL", "NULL", "NULL", "NULL", "NULL", "NULL", "NULL", "NULL", "NULL"]}, {"geom": {"pts": [[13.957741039536998, -3.3952211606673437, 10.53568483422029]], "r": 0.21969301510154957}, "mtl": 0, "prop": ["8653", "NULL", "Thuja", "plicata", "20100316", "NULL", "NULL", "NULL", "NULL", "NULL", "NULL", "NULL", "NULL", "NULL", "NULL"]}, {"geom": {"pts": [[13.893810372119564, -3.210693674122694, 10.513619490765514]], "r": 0.21969301510154957}, "mtl": 0, "prop": ["8654", "NULL", "Thuja", "plicata", "20100316", "NULL", "NULL", "NULL", "NULL", "NULL", "NULL", "NULL", "NULL", "NULL", "NULL"]}, {"geom": {"pts": [[13.880526267814853, -2.745200790642469, 10.446899671436196]], "r": 0.21969301510154957}, "mtl": 0, "prop": ["8660", "NULL", "Thuja", "plicata", "20100316", "NULL", "NULL", "NULL", "NULL", "NULL", "NULL", "NULL", "NULL", "NULL", "NULL"]}, {"geom": {"pts": [[14.068986259243788, -2.8191860750426865, 10.443578430366985]], "r": 0.21969301510154957}, "mtl": 0, "prop": ["8661", "NULL", "Thuja", "plicata", "20100316", "NULL", "NULL", "NULL", "NULL", "NULL", "NULL", "NULL", "NULL", "NULL", "NULL"]}, {"geom": {"pts": [[14.10740324449764, -2.956128054327769, 10.460627970693011]], "r": 0.21969301510154957}, "mtl": 0, "prop": ["8662", "NULL", "Thuja", "plicata", "20100316", "NULL", "NULL", "NULL", "NULL", "NULL", "NULL", "NULL", "NULL", "NULL", "NULL"]}, {"geom": {"pts": [[14.193112812785191, -2.936428914086605, 10.451358163106194]], "r": 0.21969301510154957}, "mtl": 0, "prop": ["8663", "NULL", "Acer", "macrophyllum", "20100316", "NULL", "NULL", "NULL", "NULL", "NULL", "NULL", "NULL", "NULL", "NULL", "NULL"]}, {"geom": {"pts": [[15.128448501446623, -11.674176680429612, 10.73601441886407]], "r": 0.21969301510154957}, "mtl": 0, "prop": ["9427", "NULL", "Pseudotsuga", "menziesii", "20100316", "NULL", "NULL", "NULL", "NULL", "NULL", "NULL", "NULL", "NULL", "NULL", "NULL"]}, {"geom": {"pts": [[15.038205933923987, -11.897611799669718, 10.70532541388969]], "r": 0.21969301510154957}, "mtl": 0, "prop": ["9426", "NULL", "Pseudotsuga", "menziesii", "20100316", "NULL", "NULL", "NULL", "NULL", "NULL", "NULL", "NULL", "NULL", "NULL", "NULL"]}, {"geom": {"pts": [[15.099148776381677, -12.098323338387955, 10.672718084209931]], "r": 0.21969301510154957}, "mtl": 0, "prop": ["9424", "NULL", "Pseudotsuga", "menziesii", "20100316", "NULL", "NULL", "NULL", "NULL", "NULL", "NULL", "NULL", "NULL", "NULL", "NULL"]}, {"geom": {"pts": [[15.353443441398207, -12.46376802278744, 10.603338255000805]], "r": 0.21969301510154957}, "mtl": 0, "prop": ["9418", "NULL", "Pseudotsuga", "menziesii", "20100316", "NULL", "NULL", "NULL", "NULL", "NULL", "NULL", "NULL", "NULL", "NULL", "NULL"]}, {"geom": {"pts": [[15.126559141448325, -13.542336234130742, 10.407799034715241]], "r": 0.21969301510154957}, "mtl": 0, "prop": ["9413", "NULL", "Pseudotsuga", "menziesii", "20100316", "NULL", "NULL", "NULL", "NULL", "NULL", "NULL", "NULL", "NULL", "NULL", "NULL"]}, {"geom": {"pts": [[15.050237788047083, -13.76997481321682, 10.357685420731983]], "r": 0.21969301510154957}, "mtl": 0, "prop": ["9412", "NULL", "Pseudotsuga", "menziesii", "20100316", "NULL", "NULL", "NULL", "NULL", "NULL", "NULL", "NULL", "NULL", "NULL", "NULL"]}, {"geom": {"pts": [[15.067952368204796, -14.3906368734083, 10.208877394809354]], "r": 0.21969301510154957}, "mtl": 0, "prop": ["9408", "NULL", "Pseudotsuga", "menziesii", "20100316", "NULL", "NULL", "NULL", "NULL", "NULL", "NULL", "NULL", "NULL", "NULL", "NULL"]}, {"geom": {"pts": [[15.407985893844089, 0.3986355478594609, 10.1129745685378]], "r": 0.21969301510154957}, "mtl": 0, "prop": ["8701", "NULL", "Thuja", "plicata", "20100316", "NULL", "NULL", "NULL", "NULL", "NULL", "NULL", "NULL", "NULL", "NULL", "NULL"]}, {"geom": {"pts": [[15.31430146921976, 0.5978458507966304, 10.101333882579851]], "r": 0.21969301510154957}, "mtl": 0, "prop": ["8703", "NULL", "Thuja", "plicata", "20100316", "NULL", "NULL", "NULL", "NULL", "NULL", "NULL", "NULL", "NULL", "NULL", "NULL"]}, {"geom": {"pts": [[15.2383462707673, 0.6293205368996401, 10.09843753911904]], "r": 0.21969301510154957}, "mtl": 0, "prop": ["8704", "NULL", "Thuja", "plicata", "20100316", "NULL", "NULL", "NULL", "NULL", "NULL", "NULL", "NULL", "NULL", "NULL", "NULL"]}, {"geom": {"pts": [[15.242337360466928, 0.670842516671445, 10.094774368613482]], "r": 0.21969301510154957}, "mtl": 0, "prop": ["8705", "NULL", "Thuja", "plicata", "20100316", "NULL", "NULL", "NULL", "NULL", "NULL", "NULL", "NULL", "NULL", "NULL", "NULL"]}, {"geom": {"pts": [[15.335728861125409, 0.7537473375418559, 10.088051432490035]], "r": 0.21969301510154957}, "mtl": 0, "prop": ["8707", "NULL", "Acer", "circinatum", "20100316", "NULL", "NULL", "NULL", "NULL", "NULL", "NULL", "NULL", "NULL", "NULL", "NULL"]}, {"geom": {"pts": [[12.976196586541933, -3.94777838606276, 10.689045214795442]], "r": 0.21969301510154957}, "mtl": 0, "prop": ["8637", "NULL", "Pseudotsuga", "menziesii", "20100316", "NULL", "NULL", "NULL", "NULL", "NULL", "NULL", "NULL", "NULL", "NULL", "NULL"]}, {"geom": {"pts": [[15.485947621776319, 0.8408556180536301, 10.082027440361474]], "r": 0.21969301510154957}, "mtl": 0, "prop": ["8710", "NULL", "Acer", "circinatum", "20100316", "NULL", "NULL", "NULL", "NULL", "NULL", "NULL", "NULL", "NULL", "NULL", "NULL"]}, {"geom": {"pts": [[15.491264192781173, 0.7452452179778993, 10.089756889360045]], "r": 0.21969301510154957}, "mtl": 0, "prop": ["8711", "NULL", "Thuja", "plicata", "20100316", "NULL", "NULL", "NULL", "NULL", "NULL", "NULL", "NULL", "NULL", "NULL", "NULL"]}, {"geom": {"pts": [[15.66949381283248, 0.9392707656317622, 10.076434212277718]], "r": 0.21969301510154957}, "mtl": 0, "prop": ["8713", "NULL", "Acer", "macrophyllum", "20100316", "NULL", "NULL", "NULL", "NULL", "NULL", "NULL", "NULL", "NULL", "NULL", "NULL"]}, {"geom": {"pts": [[14.252041802542903, 4.354061822772588, 9.739036179025849]], "r": 0.21969301510154957}, "mtl": 0, "prop": ["8736", "NULL", "Acer", "rubrum", "20100316", "NULL", "NULL", "NULL", "NULL", "NULL", "NULL", "NULL", "NULL", "NULL", "NULL"]}, {"geom": {"pts": [[14.940420572874135, 2.9967837293001236, 9.870617833467868]], "r": 0.21969301510154957}, "mtl": 0, "prop": ["8723", "NULL", "Acer", "macrophyllum", "20100316", "NULL", "NULL", "NULL", "NULL", "NULL", "NULL", "NULL", "NULL", "NULL", "NULL"]}, {"geom": {"pts": [[16.040328299168582, 3.2714732291259123, 9.94171736660685]], "r": 0.21969301510154957}, "mtl": 0, "prop": ["8729", "NULL", "Acer", "macrophyllum", "20100316", "NULL", "NULL", "NULL", "NULL", "NULL", "NULL", "NULL", "NULL", "NULL", "NULL"]}, {"geom": {"pts": [[15.70619719264913, 3.0988823964487056, 9.925399454707122]], "r": 0.21969301510154957}, "mtl": 0, "prop": ["8730", "NULL", "Thuja", "plicata", "20100316", "NULL", "NULL", "NULL", "NULL", "NULL", "NULL", "NULL", "NULL", "NULL", "NULL"]}, {"geom": {"pts": [[20.814557764485897, -1.3652723472559654, 10.45072207378711]], "r": 0.21969301510154957}, "mtl": 0, "prop": ["6836", "NULL", "Pseudotsuga", "menziesii", "20100316", "NULL", "NULL", "NULL", "NULL", "NULL", "NULL", "NULL", "NULL", "NULL", "NULL"]}, {"geom": {"pts": [[21.078189382691303, -1.5740026809757608, 10.508892819145439]], "r": 0.21969301510154957}, "mtl": 0, "prop": ["6837", "NULL", "Pseudotsuga", "menziesii", "20100316", "NULL", "NULL", "NULL", "NULL", "NULL", "NULL", "NULL", "NULL", "NULL", "NULL"]}, {"geom": {"pts": [[15.276118823095096, 1.3913330828243524, 10.031907121879462]], "r": 0.21969301510154957}, "mtl": 0, "prop": ["9991803", "NULL", "NULL", "NULL", "20100316", "NULL", "NULL", "NULL", "NULL", "NULL", "NULL", "NULL", "NULL", "NULL", "NULL"]}, {"geom": {"pts": [[13.260515963646036, -3.8740933486823566, 10.656743777871236]], "r": 0.21969301510154957}, "mtl": 0, "prop": ["8644", "NULL", "Alnus", "rubra", "20100316", "NULL", "NULL", "NULL", "NULL", "NULL", "NULL", "NULL", "NULL", "NULL", "NULL"]}, {"geom": {"pts": [[15.629436453154188, 3.3399808343792734, 9.907941778019575]], "r": 0.21969301510154957}, "mtl": 0, "prop": ["8731", "NULL", "Thuja", "plicata", "20100316", "NULL", "NULL", "NULL", "NULL", "NULL", "NULL", "NULL", "NULL", "NULL", "NULL"]}, {"geom": {"pts": [[13.532210315432536, 5.725107345333818, 9.762279000073923]], "r": 0.21969301510154957}, "mtl": 0, "prop": ["8746", "NULL", "Thuja", "plicata", "20100316", "NULL", "NULL", "NULL", "NULL", "NULL", "NULL", "NULL", "NULL", "NULL", "NULL"]}, {"geom": {"pts": [[13.867234840396502, 6.410190720341708, 9.871978008652157]], "r": 0.21969301510154957}, "mtl": 0, "prop": ["8747", "NULL", "Thuja", "plicata", "20100316", "NULL", "NULL", "NULL", "NULL", "NULL", "NULL", "NULL", "NULL", "NULL", "NULL"]}, {"geom": {"pts": [[13.636264250499853, 6.522651574832432, 9.880796938697909]], "r": 0.21969301510154957}, "mtl": 0, "prop": ["8748", "NULL", "Thuja", "plicata", "20100316", "NULL", "NULL", "NULL", "NULL", "NULL", "NULL", "NULL", "NULL", "NULL", "NULL"]}, {"geom": {"pts": [[12.502977832166684, 6.87336218115474, 9.777364960327994]], "r": 0.21969301510154957}, "mtl": 0, "prop": ["8759", "NULL", "Thuja", "plicata", "20100316", "NULL", "NULL", "NULL", "NULL", "NULL", "NULL", "NULL", "NULL", "NULL", "NULL"]}, {"geom": {"pts": [[12.562748978334726, 6.774126846076669, 9.771858890728012]], "r": 0.21969301510154957}, "mtl": 0, "prop": ["8760", "NULL", "Tsuga", "heterophylla", "20100316", "NULL", "NULL", "NULL", "NULL", "NULL", "NULL", "NULL", "NULL", "NULL", "NULL"]}]}