{"type": "block", "layer": 1, "block": 23, "features": [{"geom": {"pts": [[31.9617227659041, -8.278755224021488, 9.865827469109652]], "r": 0.07323100503384986, "h": 0.5492325377538739}, "mtl": 0, "prop": ["9999970", "NULL", "NULL", "NULL", "20060101", "NULL", "NULL", "NULL", "NULL", "NULL", "NULL", "NULL", "NULL", "NULL", "NULL"]}, {"geom": {"pts": [[33.04687444467815, -10.32728274335888, 9.708968178248362]], "r": 0.07323100503384986, "h": 0.5492325377538739}, "mtl": 0, "prop": ["9999971", "NULL", "NULL", "NULL", "20060101", "NULL", "NULL", "NULL", "NULL", "NULL", "NULL", "NULL", "NULL", "NULL", "NULL"]}, {"geom": {"pts": [[33.453445661561176, -11.083488070491876, 9.622558922209466]], "r": 0.07323100503384986, "h": 0.5492325377538739}, "mtl": 0, "prop": ["9999972", "NULL", "NULL", "NULL", "20060101", "NULL", "NULL", "NULL", "NULL", "NULL", "NULL", "NULL", "NULL", "NULL", "NULL"]}, {"geom": {"pts": [[25.5926098881918, 19.58715807318027, 8.128641558757334]], "r": 0.07323100503384986, "h": 0.5492325377538739}, "mtl": 0, "prop": ["6086", "NULL", "NULL", "NULL", "20060101", "NULL", "NULL", "NULL", "NULL", "NULL", "NULL", "NULL", "NULL", "NULL", "NULL"]}, {"geom": {"pts": [[46.58801226239739, 16.74225069725599, 9.498099121566629]], "r": 0.07323100503384986, "h": 0.5492325377538739}, "mtl": 0, "prop": ["1773", "Ash", "Fraxinus", "NULL", "NULL", "NULL", "NULL", "NULL", "NULL", "NULL", "G", "NULL", "NULL", "NULL", "NULL"]}, {"geom": {"pts": [[41.16858835046075, 27.17639469500632, 8.677874096511207]], "r": 0.07323100503384986, "h": 0.5492325377538739}, "mtl": 0, "prop": ["6155", "Katsura tree", "Cercidiphyllum", "japonicum", "20060101", "NULL", "NULL", "NULL", "NULL", "NULL", "NULL", "NULL", "NULL", "NULL", "NULL"]}, {"geom": {"pts": [[26.527703914644484, 19.98977481581252, 8.128641558757334]], "r": 0.07323100503384986, "h": 0.5492325377538739}, "mtl": 0, "prop": ["6088", "NULL", "NULL", "NULL", "20060101", "NULL", "NULL", "NULL", "NULL", "NULL", "NULL", "NULL", "NULL", "NULL", "NULL"]}, {"geom": {"pts": [[38.381826392473386, 28.24551610685684, 8.420003989391775]], "r": 0.07323100503384986, "h": 0.5492325377538739}, "mtl": 0, "prop": ["6175", "NULL", "NULL", "NULL", "20060101", "NULL", "NULL", "NULL", "NULL", "NULL", "NULL", "NULL", "NULL", "NULL", "NULL"]}, {"geom": {"pts": [[17.093748983591173, -26.163165365440932, 9.117260126714307]], "r": 0.07323100503384986, "h": 0.5492325377538739}, "mtl": 0, "prop": ["9999308", "NULL", "NULL", "NULL", "19041201", "NULL", "NULL", "NULL", "NULL", "NULL", "NULL", "NULL", "NULL", "NULL", "NULL"]}, {"geom": {"pts": [[22.332958715375995, 27.380731168522292, 7.276142752835059]], "r": 0.07323100503384986, "h": 0.5492325377538739}, "mtl": 0, "prop": ["9999378", "NULL", "NULL", "NULL", "19041201", "NULL", "NULL", "NULL", "NULL", "NULL", "NULL", "NULL", "NULL", "NULL", "NULL"]}, {"geom": {"pts": [[24.43881146531215, 24.061235618124858, 7.885523863079065]], "r": 0.07323100503384986, "h": 0.5492325377538739}, "mtl": 0, "prop": ["9999730", "NULL", "Acer", "NULL", "20060101", "NULL", "NULL", "NULL", "NULL", "NULL", "NULL", "NULL", "NULL", "NULL", "NULL"]}, {"geom": {"pts": [[41.21810715602108, -28.516875775133382, 9.482416460923641]], "r": 0.07323100503384986, "h": 0.5492325377538739}, "mtl": 0, "prop": ["9999985", "Magnolia", "Magnolia", "NULL", "20060101", "NULL", "NULL", "NULL", "NULL", "NULL", "NULL", "NULL", "NULL", "NULL", "NULL"]}, {"geom": {"pts": [[48.97086128907663, -26.690699556297666, 10.335744110504116]], "r": 0.07323100503384986, "h": 0.5492325377538739}, "mtl": 0, "prop": ["7847", "Hormbeam, Fastigiate", "Carpinus", "betulus", "NULL", "Fastigiata", "NULL", "NULL", "NULL", "NULL", "G", "NULL", "NULL", "NULL", "NULL"]}, {"geom": {"pts": [[39.05648167254687, 27.03344045012273, 8.569388602207065]], "r": 0.07323100503384986, "h": 0.5492325377538739}, "mtl": 0, "prop": ["6152", "Katsura tree", "Cercidiphyllum", "japonicum", "20060101", "NULL", "NULL", "NULL", "NULL", "NULL", "NULL", "NULL", "NULL", "NULL", "NULL"]}, {"geom": {"pts": [[43.18262406630209, 14.342419400576528, 9.679150758111728]], "r": 0.07323100503384986, "h": 0.5492325377538739}, "mtl": 0, "prop": ["5671", "Ash, Caucasian", "Fraxinus", "oxycarpa", "NULL", "Raywood", "NULL", "NULL", "NULL", "NULL", "G", "NULL", "NULL", "NULL", "NULL"]}, {"geom": {"pts": [[49.52155112387432, -27.794356710108623, 10.39351593818671]], "r": 0.07323100503384986, "h": 0.5492325377538739}, "mtl": 0, "prop": ["7842", "Hormbeam, Fastigiate", "Carpinus", "betulus", "NULL", "Fastigiata", "NULL", "NULL", "NULL", "NULL", "G", "NULL", "NULL", "NULL", "NULL"]}, {"geom": {"pts": [[33.388379913648215, 4.078083457196994, 9.582206220346599]], "r": 0.07323100503384986, "h": 0.5492325377538739}, "mtl": 0, "prop": ["141", "Birch, Cutleaf", "Betula", "pendula", "NULL", "Dalecarlica", "NULL", "NULL", "NULL", "NULL", "F", "NULL", "NULL", "NULL", "NULL"]}, {"geom": {"pts": [[49.03879036933717, -26.808996921932366, 10.342437714445524]], "r": 0.07323100503384986, "h": 0.5492325377538739}, "mtl": 0, "prop": ["7846", "Hormbeam, Fastigiate", "Carpinus", "betulus", "NULL", "Fastigiata", "NULL", "NULL", "NULL", "NULL", "G", "NULL", "NULL", "NULL", "NULL"]}, {"geom": {"pts": [[44.02956260882128, 15.216739015869823, 9.659109335217675]], "r": 0.07323100503384986, "h": 0.5492325377538739}, "mtl": 0, "prop": ["5674", "Ash, Caucasian", "Fraxinus", "oxycarpa", "NULL", "Raywood", "NULL", "NULL", "NULL", "NULL", "G", "NULL", "NULL", "NULL", "NULL"]}, {"geom": {"pts": [[42.10385813127847, 14.185551264706493, 9.75139005603853]], "r": 0.07323100503384986, "h": 0.5492325377538739}, "mtl": 0, "prop": ["5660", "Ash, Caucasian", "Fraxinus", "oxycarpa", "NULL", "Raywood", "NULL", "NULL", "NULL", "NULL", "G", "NULL", "NULL", "NULL", "NULL"]}, {"geom": {"pts": [[41.762528416792776, -10.401568274847106, 10.10587869467128]], "r": 0.07323100503384986, "h": 0.5492325377538739}, "mtl": 0, "prop": ["9999979", "Katsura tree", "Cercidiphyllum", "japonicum", "20060101", "NULL", "NULL", "NULL", "NULL", "NULL", "NULL", "NULL", "NULL", "NULL", "NULL"]}, {"geom": {"pts": [[44.46161089247872, 2.6334627439855125, 10.093668126319422]], "r": 0.07323100503384986, "h": 0.5492325377538739}, "mtl": 0, "prop": ["9999907", "Indian Bean Tree", "Catalpa", "bignoides", "20060101", "NULL", "NULL", "NULL", "NULL", "NULL", "NULL", "NULL", "NULL", "NULL", "NULL"]}, {"geom": {"pts": [[38.38296879611666, -9.135675152544822, 9.937842166328265]], "r": 0.07323100503384986, "h": 0.5492325377538739}, "mtl": 0, "prop": ["5949", "Linden", "Tilia", "NULL", "NULL", "NULL", "NULL", "NULL", "NULL", "NULL", "S", "Class Tree - 1923", "NULL", "NULL", "NULL"]}, {"geom": {"pts": [[32.65029193691713, -16.822894859003046, 9.079231371731309]], "r": 0.07323100503384986, "h": 0.5492325377538739}, "mtl": 0, "prop": ["4704", "Magnolia", "Magnolia", "NULL", "NULL", "NULL", "NULL", "NULL", "NULL", "NULL", "F", "NULL", "NULL", "NULL", "NULL"]}, {"geom": {"pts": [[48.30926309713032, 0.8169017562136482, 10.014686616835263]], "r": 0.07323100503384986, "h": 0.5492325377538739}, "mtl": 0, "prop": ["5808", "Cypress", "Chamaecyparis", "NULL", "NULL", "NULL", "NULL", "NULL", "NULL", "NULL", "G", "NULL", "NULL", "NULL", "NULL"]}, {"geom": {"pts": [[31.20977216008861, 1.195791653281499, 9.698231761559573]], "r": 0.07323100503384986, "h": 0.5492325377538739}, "mtl": 0, "prop": ["183", "Holly", "Ilex", "NULL", "NULL", "NULL", "NULL", "NULL", "NULL", "NULL", "G", "NULL", "NULL", "NULL", "NULL"]}, {"geom": {"pts": [[22.32132230856674, -28.353753711485947, 9.004909488879706]], "r": 0.07323100503384986, "h": 0.5492325377538739}, "mtl": 0, "prop": ["4567", "Cedar", "Cedrus", "NULL", "NULL", "NULL", "NULL", "NULL", "NULL", "NULL", "G", "NULL", "Caution - Missing tag", "NULL", "NULL"]}, {"geom": {"pts": [[36.126179621637654, 8.783380577565216, 9.666492664468182]], "r": 0.07323100503384986, "h": 0.5492325377538739}, "mtl": 0, "prop": ["70", "Pine", "Pinus", "NULL", "NULL", "NULL", "NULL", "NULL", "NULL", "NULL", "F", "NULL", "NULL", "NULL", "NULL"]}, {"geom": {"pts": [[48.888652162731674, 3.5417395763956168, 10.184608785452243]], "r": 0.07323100503384986, "h": 0.5492325377538739}, "mtl": 0, "prop": ["5754", "Spruce ROW", "Picea", "NULL", "NULL", "NULL", "NULL", "NULL", "NULL", "NULL", "G", "NULL", "NULL", "NULL", "NULL"]}, {"geom": {"pts": [[44.15283235964835, -10.004868597395728, 10.075171252325333]], "r": 0.07323100503384986, "h": 0.5492325377538739}, "mtl": 0, "prop": ["5976", "Hazelnut, Great, 'Purple Filbert", "Corylus", "maxima", "NULL", "Purpurea", "NULL", "NULL", "NULL", "NULL", "G", "NULL", "NULL", "NULL", "NULL"]}, {"geom": {"pts": [[45.75667192405615, 1.8464711022551001, 10.118585395930777]], "r": 0.07323100503384986, "h": 0.5492325377538739}, "mtl": 0, "prop": ["5852", "Cypress, Sawara", "Chamaecyparis", "pisifera", "NULL", "Filifera", "NULL", "NULL", "NULL", "NULL", "G", "NULL", "NULL", "NULL", "NULL"]}, {"geom": {"pts": [[35.83630201124749, -15.558634788339775, 9.36597943109977]], "r": 0.07323100503384986, "h": 0.5492325377538739}, "mtl": 0, "prop": ["4788", "Maple, Norway", "Acer", "platanoides", "NULL", "Crimson King", "NULL", "NULL", "NULL", "NULL", "G", "NULL", "Tag/Nail in Tree", "NULL", "NULL"]}, {"geom": {"pts": [[45.75147252270328, 10.688368003950927, 9.594851743054985]], "r": 0.07323100503384986, "h": 0.5492325377538739}, "mtl": 0, "prop": ["5721", "Pine, Shore", "Pinus", "contorta", "NULL", "Contorta", "NULL", "NULL", "NULL", "NULL", "G", "NULL", "NULL", "NULL", "NULL"]}, {"geom": {"pts": [[49.17713838405389, -27.07823071194369, 10.360388171791334]], "r": 0.07323100503384986, "h": 0.5492325377538739}, "mtl": 0, "prop": ["7844", "Hormbeam, Fastigiate", "Carpinus", "betulus", "NULL", "Fastigiata", "NULL", "NULL", "NULL", "NULL", "G", "NULL", "NULL", "NULL", "NULL"]}, {"geom": {"pts": [[40.49884687078137, 13.323827382229368, 9.734734405014175]], "r": 0.07323100503384986, "h": 0.5492325377538739}, "mtl": 0, "prop": ["5666", "Ash, Caucasian", "Fraxinus", "oxycarpa", "NULL", "Raywood", "NULL", "NULL", "NULL", "NULL", "G", "NULL", "NULL", "NULL", "NULL"]}, {"geom": {"pts": [[45.002846604422764, 15.896996467932537, 9.624894601962152]], "r": 0.07323100503384986, "h": 0.5492325377538739}, "mtl": 0, "prop": ["5676", "Ash, Caucasian", "Fraxinus", "oxycarpa", "NULL", "Raywood", "NULL", "NULL", "NULL", "NULL", "F", "NULL", "NULL", "NULL", "NULL"]}, {"geom": {"pts": [[39.41159346211843, 12.741003782648459, 9.68928460797519]], "r": 0.07323100503384986, "h": 0.5492325377538739}, "mtl": 0, "prop": ["5664", "Ash, Caucasian", "Fraxinus", "oxycarpa", "NULL", "Raywood", "NULL", "NULL", "NULL", "NULL", "G", "NULL", "Tag in Tree", "NULL", "NULL"]}, {"geom": {"pts": [[37.59708294261055, -15.273443962089429, 9.665393964735216]], "r": 0.07323100503384986, "h": 0.5492325377538739}, "mtl": 0, "prop": ["5996", "Cypress, Sawara", "Chamaecyparis", "pisifera", "NULL", "Boulevard", "NULL", "NULL", "NULL", "NULL", "G", "NULL", "NULL", "NULL", "NULL"]}, {"geom": {"pts": [[39.94757118801788, 13.026194608489595, 9.71811227648358]], "r": 0.07323100503384986, "h": 0.5492325377538739}, "mtl": 0, "prop": ["5665", "Ash, Caucasian", "Fraxinus", "oxycarpa", "NULL", "Raywood", "NULL", "NULL", "NULL", "NULL", "G", "NULL", "NULL", "NULL", "NULL"]}, {"geom": {"pts": [[47.54079889962852, -20.746839124997912, 10.66878924794133]], "r": 0.07323100503384986, "h": 0.5492325377538739}, "mtl": 0, "prop": ["7683", "Oak, English", "Quercus", "robur", "NULL", "fastigiata", "NULL", "NULL", "NULL", "NULL", "G", "NULL", "NULL", "NULL", "NULL"]}, {"geom": {"pts": [[45.13006350627615, 8.022459173466991, 9.834519136063069]], "r": 0.07323100503384986, "h": 0.5492325377538739}, "mtl": 0, "prop": ["5727", "Cottonwood, Black", "Populus", "trichocarpa", "NULL", "tricocarpa", "NULL", "NULL", "NULL", "NULL", "G", "NULL", "NULL", "NULL", "NULL"]}, {"geom": {"pts": [[49.60046485490442, -27.91330583153579, 10.399807272203002]], "r": 0.07323100503384986, "h": 0.5492325377538739}, "mtl": 0, "prop": ["7841", "Hormbeam, Fastigiate", "Carpinus", "betulus", "NULL", "Fastigiata", "NULL", "NULL", "NULL", "NULL", "G", "NULL", "NULL", "NULL", "NULL"]}, {"geom": {"pts": [[49.0860023982615, -26.960885349462277, 10.348545512808485]], "r": 0.07323100503384986, "h": 0.5492325377538739}, "mtl": 0, "prop": ["7845", "Hormbeam, Fastigiate", "Carpinus", "betulus", "NULL", "Fastigiata", "NULL", "NULL", "NULL", "NULL", "G", "NULL", "NULL", "NULL", "NULL"]}, {"geom": {"pts": [[39.521176338034294, 13.871009451983625, 9.723113832552482]], "r": 0.07323100503384986, "h": 0.5492325377538739}, "mtl": 0, "prop": ["5657", "Ash, Caucasian", "Fraxinus", "oxycarpa", "NULL", "Raywood", "NULL", "NULL", "NULL", "NULL", "G", "NULL", "NULL", "NULL", "NULL"]}, {"geom": {"pts": [[42.94164279815138, -10.653424347284457, 10.10587869467128]], "r": 0.07323100503384986, "h": 0.5492325377538739}, "mtl": 0, "prop": ["5973", "Hazelnut, Great, 'Purple Filbert", "Corylus", "maxima", "NULL", "Purpurea", "NULL", "NULL", "NULL", "NULL", "G", "NULL", "NULL", "NULL", "NULL"]}, {"geom": {"pts": [[39.071794275706374, 12.552946561723706, 9.676140438172133]], "r": 0.07323100503384986, "h": 0.5492325377538739}, "mtl": 0, "prop": ["5663", "Ash, Caucasian", "Fraxinus", "oxycarpa", "NULL", "Raywood", "NULL", "NULL", "NULL", "NULL", "G", "NULL", "Tag in Tree", "NULL", "NULL"]}, {"geom": {"pts": [[42.59869467842873, 14.44805512532967, 9.727556401037944]], "r": 0.07323100503384986, "h": 0.5492325377538739}, "mtl": 0, "prop": ["1772", "Ash, Caucasian", "Fraxinus", "oxycarpa", "NULL", "Raywood", "NULL", "NULL", "NULL", "NULL", "G", "NULL", "NULL", "NULL", "NULL"]}, {"geom": {"pts": [[23.199676952177526, 23.432569409312556, 7.887132104717172]], "r": 0.07323100503384986, "h": 0.5492325377538739}, "mtl": 0, "prop": ["9999729", "NULL", "Prunus", "pissardii", "20060101", "NULL", "NULL", "NULL", "NULL", "NULL", "NULL", "NULL", "NULL", "NULL", "NULL"]}, {"geom": {"pts": [[28.083430708655055, -28.60892714861316, 9.095921383311767]], "r": 0.07323100503384986, "h": 0.5492325377538739}, "mtl": 0, "prop": ["9999938", "Pacific Dogwood", "Cornus", "nuttallii", "20060101", "NULL", "NULL", "NULL", "NULL", "NULL", "NULL", "NULL", "NULL", "NULL", "NULL"]}, {"geom": {"pts": [[42.17684015091322, -8.248693896438175, 10.099206880350817]], "r": 0.07323100503384986, "h": 0.5492325377538739}, "mtl": 0, "prop": ["5981", "Katsura", "Cercidiphyllum", "japonicum", "NULL", "NULL", "NULL", "NULL", "NULL", "NULL", "G", "NULL", "NULL", "NULL", "NULL"]}]}